[
{"train_mad": {"data": 2.8030617476583264, "label": "train_mad", "epoch": 0, "counter": 0}},
{"train_mse": {"data": 36.185061050998215, "label": "train_mse", "epoch": 0, "counter": 0}},
{"train_mape": {"data": 136.8127684826718, "label": "train_mape", "epoch": 0, "counter": 0}},
{"train_msle": {"data": 1.6529253629921792, "label": "train_msle", "epoch": 0, "counter": 0}},
{"train_r2": {"data": 0.013273076752021828, "label": "train_r2", "epoch": 0, "counter": 0}},
{"train_kappa": {"data": 0.2596866621155661, "label": "train_kappa", "epoch": 0, "counter": 0}},
{"val_mad": {"data": 2.5688793994463426, "label": "val_mad", "epoch": 0, "counter": 0}},
{"val_mse": {"data": 56.649019111574795, "label": "val_mse", "epoch": 0, "counter": 0}},
{"val_mape": {"data": 110.49584268209851, "label": "val_mape", "epoch": 0, "counter": 0}},
{"val_msle": {"data": 1.3358663620855007, "label": "val_msle", "epoch": 0, "counter": 0}},
{"val_r2": {"data": 0.08239919931830786, "label": "val_r2", "epoch": 0, "counter": 0}},
{"val_kappa": {"data": 0.3741689422767237, "label": "val_kappa", "epoch": 0, "counter": 0}},
{"train_mad": {"data": 2.6378462811229006, "label": "train_mad", "epoch": 1, "counter": 1}},
{"train_mse": {"data": 33.97862149163635, "label": "train_mse", "epoch": 1, "counter": 1}},
{"train_mape": {"data": 124.25289817351317, "label": "train_mape", "epoch": 1, "counter": 1}},
{"train_msle": {"data": 1.4403964006322774, "label": "train_msle", "epoch": 1, "counter": 1}},
{"train_r2": {"data": 0.0733515941460191, "label": "train_r2", "epoch": 1, "counter": 1}},
{"train_kappa": {"data": 0.354232944007818, "label": "train_kappa", "epoch": 1, "counter": 1}},
{"val_mad": {"data": 2.400705514129973, "label": "val_mad", "epoch": 1, "counter": 1}},
{"val_mse": {"data": 54.694465376507175, "label": "val_mse", "epoch": 1, "counter": 1}},
{"val_mape": {"data": 94.08220718351694, "label": "val_mape", "epoch": 1, "counter": 1}},
{"val_msle": {"data": 1.1450673669080476, "label": "val_msle", "epoch": 1, "counter": 1}},
{"val_r2": {"data": 0.11405906034327984, "label": "val_r2", "epoch": 1, "counter": 1}},
{"val_kappa": {"data": 0.4481315653734409, "label": "val_kappa", "epoch": 1, "counter": 1}},
{"train_mad": {"data": 2.5648801225422324, "label": "train_mad", "epoch": 2, "counter": 2}},
{"train_mse": {"data": 33.59534420770762, "label": "train_mse", "epoch": 2, "counter": 2}},
{"train_mape": {"data": 116.68564618994652, "label": "train_mape", "epoch": 2, "counter": 2}},
{"train_msle": {"data": 1.3352278805963598, "label": "train_msle", "epoch": 2, "counter": 2}},
{"train_r2": {"data": 0.08383727883958536, "label": "train_r2", "epoch": 2, "counter": 2}},
{"train_kappa": {"data": 0.401436777316048, "label": "train_kappa", "epoch": 2, "counter": 2}},
{"val_mad": {"data": 2.3377811475562043, "label": "val_mad", "epoch": 2, "counter": 2}},
{"val_mse": {"data": 54.41871808593067, "label": "val_mse", "epoch": 2, "counter": 2}},
{"val_mape": {"data": 86.35924478351194, "label": "val_mape", "epoch": 2, "counter": 2}},
{"val_msle": {"data": 1.0596734922449216, "label": "val_msle", "epoch": 2, "counter": 2}},
{"val_r2": {"data": 0.11852561490304114, "label": "val_r2", "epoch": 2, "counter": 2}},
{"val_kappa": {"data": 0.457485537312744, "label": "val_kappa", "epoch": 2, "counter": 2}},
{"train_mad": {"data": 2.526809740255138, "label": "train_mad", "epoch": 3, "counter": 3}},
{"train_mse": {"data": 33.30509360888499, "label": "train_mse", "epoch": 3, "counter": 3}},
{"train_mape": {"data": 112.52027739203257, "label": "train_mape", "epoch": 3, "counter": 3}},
{"train_msle": {"data": 1.277465370158769, "label": "train_msle", "epoch": 3, "counter": 3}},
{"train_r2": {"data": 0.09173459381841043, "label": "train_r2", "epoch": 3, "counter": 3}},
{"train_kappa": {"data": 0.4262908245011473, "label": "train_kappa", "epoch": 3, "counter": 3}},
{"val_mad": {"data": 2.223406905093971, "label": "val_mad", "epoch": 3, "counter": 3}},
{"val_mse": {"data": 52.16461457756747, "label": "val_mse", "epoch": 3, "counter": 3}},
{"val_mape": {"data": 81.72015452149599, "label": "val_mape", "epoch": 3, "counter": 3}},
{"val_msle": {"data": 0.9582130859300428, "label": "val_msle", "epoch": 3, "counter": 3}},
{"val_r2": {"data": 0.1550375830982833, "label": "val_r2", "epoch": 3, "counter": 3}},
{"val_kappa": {"data": 0.5169722420654312, "label": "val_kappa", "epoch": 3, "counter": 3}},
{"train_mad": {"data": 2.4834185388758385, "label": "train_mad", "epoch": 4, "counter": 4}},
{"train_mse": {"data": 33.37363545142246, "label": "train_mse", "epoch": 4, "counter": 4}},
{"train_mape": {"data": 108.17323161856098, "label": "train_mape", "epoch": 4, "counter": 4}},
{"train_msle": {"data": 1.214589046102531, "label": "train_msle", "epoch": 4, "counter": 4}},
{"train_r2": {"data": 0.0898626142432356, "label": "train_r2", "epoch": 4, "counter": 4}},
{"train_kappa": {"data": 0.4538540776993878, "label": "train_kappa", "epoch": 4, "counter": 4}},
{"val_mad": {"data": 2.2113980755558247, "label": "val_mad", "epoch": 4, "counter": 4}},
{"val_mse": {"data": 51.802006457515354, "label": "val_mse", "epoch": 4, "counter": 4}},
{"val_mape": {"data": 74.52028579683255, "label": "val_mape", "epoch": 4, "counter": 4}},
{"val_msle": {"data": 0.9179398353155123, "label": "val_msle", "epoch": 4, "counter": 4}},
{"val_r2": {"data": 0.16091110935719632, "label": "val_r2", "epoch": 4, "counter": 4}},
{"val_kappa": {"data": 0.5303640865598309, "label": "val_kappa", "epoch": 4, "counter": 4}},
{"train_mad": {"data": 2.4630348203013903, "label": "train_mad", "epoch": 5, "counter": 5}},
{"train_mse": {"data": 33.38299221066785, "label": "train_mse", "epoch": 5, "counter": 5}},
{"train_mape": {"data": 105.49103301659048, "label": "train_mape", "epoch": 5, "counter": 5}},
{"train_msle": {"data": 1.1819325083506897, "label": "train_msle", "epoch": 5, "counter": 5}},
{"train_r2": {"data": 0.08962122419576879, "label": "train_r2", "epoch": 5, "counter": 5}},
{"train_kappa": {"data": 0.46680205626722715, "label": "train_kappa", "epoch": 5, "counter": 5}},
{"val_mad": {"data": 2.104719533379073, "label": "val_mad", "epoch": 5, "counter": 5}},
{"val_mse": {"data": 50.9224069911797, "label": "val_mse", "epoch": 5, "counter": 5}},
{"val_mape": {"data": 75.28363046694098, "label": "val_mape", "epoch": 5, "counter": 5}},
{"val_msle": {"data": 0.8514613581911248, "label": "val_msle", "epoch": 5, "counter": 5}},
{"val_r2": {"data": 0.17515886134384773, "label": "val_r2", "epoch": 5, "counter": 5}},
{"val_kappa": {"data": 0.5619217370719058, "label": "val_kappa", "epoch": 5, "counter": 5}},
{"train_mad": {"data": 2.4325432926134862, "label": "train_mad", "epoch": 6, "counter": 6}},
{"train_mse": {"data": 33.34147171327891, "label": "train_mse", "epoch": 6, "counter": 6}},
{"train_mape": {"data": 102.3994788946553, "label": "train_mape", "epoch": 6, "counter": 6}},
{"train_msle": {"data": 1.1399749854934451, "label": "train_msle", "epoch": 6, "counter": 6}},
{"train_r2": {"data": 0.09078884039178414, "label": "train_r2", "epoch": 6, "counter": 6}},
{"train_kappa": {"data": 0.4850109714605483, "label": "train_kappa", "epoch": 6, "counter": 6}},
{"val_mad": {"data": 2.072367427756097, "label": "val_mad", "epoch": 6, "counter": 6}},
{"val_mse": {"data": 50.127495280584704, "label": "val_mse", "epoch": 6, "counter": 6}},
{"val_mape": {"data": 72.11416640724089, "label": "val_mape", "epoch": 6, "counter": 6}},
{"val_msle": {"data": 0.8174918328606482, "label": "val_msle", "epoch": 6, "counter": 6}},
{"val_r2": {"data": 0.18803484107928825, "label": "val_r2", "epoch": 6, "counter": 6}},
{"val_kappa": {"data": 0.5867254570118274, "label": "val_kappa", "epoch": 6, "counter": 6}},
{"train_mad": {"data": 2.4110783279994523, "label": "train_mad", "epoch": 7, "counter": 7}},
{"train_mse": {"data": 33.32841353414597, "label": "train_mse", "epoch": 7, "counter": 7}},
{"train_mape": {"data": 99.96853144291872, "label": "train_mape", "epoch": 7, "counter": 7}},
{"train_msle": {"data": 1.1094431988193876, "label": "train_msle", "epoch": 7, "counter": 7}},
{"train_r2": {"data": 0.0905297872558054, "label": "train_r2", "epoch": 7, "counter": 7}},
{"train_kappa": {"data": 0.49742125324479536, "label": "train_kappa", "epoch": 7, "counter": 7}},
{"val_mad": {"data": 2.0274193878008906, "label": "val_mad", "epoch": 7, "counter": 7}},
{"val_mse": {"data": 50.1457656985132, "label": "val_mse", "epoch": 7, "counter": 7}},
{"val_mape": {"data": 68.26420168780581, "label": "val_mape", "epoch": 7, "counter": 7}},
{"val_msle": {"data": 0.7705594606009843, "label": "val_msle", "epoch": 7, "counter": 7}},
{"val_r2": {"data": 0.1877388968531939, "label": "val_r2", "epoch": 7, "counter": 7}},
{"val_kappa": {"data": 0.6037991233309845, "label": "val_kappa", "epoch": 7, "counter": 7}},
{"train_mad": {"data": 2.394895366170762, "label": "train_mad", "epoch": 8, "counter": 8}},
{"train_mse": {"data": 33.29719562851171, "label": "train_mse", "epoch": 8, "counter": 8}},
{"train_mape": {"data": 97.98058578267003, "label": "train_mape", "epoch": 8, "counter": 8}},
{"train_msle": {"data": 1.081307092101234, "label": "train_msle", "epoch": 8, "counter": 8}},
{"train_r2": {"data": 0.09194054544071939, "label": "train_r2", "epoch": 8, "counter": 8}},
{"train_kappa": {"data": 0.5076903755403919, "label": "train_kappa", "epoch": 8, "counter": 8}},
{"val_mad": {"data": 2.0010587625607523, "label": "val_mad", "epoch": 8, "counter": 8}},
{"val_mse": {"data": 49.374981566836, "label": "val_mse", "epoch": 8, "counter": 8}},
{"val_mape": {"data": 64.53043689895944, "label": "val_mape", "epoch": 8, "counter": 8}},
{"val_msle": {"data": 0.745584085684114, "label": "val_msle", "epoch": 8, "counter": 8}},
{"val_r2": {"data": 0.20022405806996124, "label": "val_r2", "epoch": 8, "counter": 8}},
{"val_kappa": {"data": 0.6116180350667368, "label": "val_kappa", "epoch": 8, "counter": 8}},
{"train_mad": {"data": 2.3676789052633413, "label": "train_mad", "epoch": 9, "counter": 9}},
{"train_mse": {"data": 32.97356059523066, "label": "train_mse", "epoch": 9, "counter": 9}},
{"train_mape": {"data": 95.71715881040038, "label": "train_mape", "epoch": 9, "counter": 9}},
{"train_msle": {"data": 1.0509629853790932, "label": "train_msle", "epoch": 9, "counter": 9}},
{"train_r2": {"data": 0.10079197303165632, "label": "train_r2", "epoch": 9, "counter": 9}},
{"train_kappa": {"data": 0.5209852400096271, "label": "train_kappa", "epoch": 9, "counter": 9}},
{"val_mad": {"data": 1.973241292937008, "label": "val_mad", "epoch": 9, "counter": 9}},
{"val_mse": {"data": 49.33382542869589, "label": "val_mse", "epoch": 9, "counter": 9}},
{"val_mape": {"data": 64.46282277037466, "label": "val_mape", "epoch": 9, "counter": 9}},
{"val_msle": {"data": 0.7103616258621455, "label": "val_msle", "epoch": 9, "counter": 9}},
{"val_r2": {"data": 0.20089070518764474, "label": "val_r2", "epoch": 9, "counter": 9}},
{"val_kappa": {"data": 0.6163631350106854, "label": "val_kappa", "epoch": 9, "counter": 9}},
{"train_mad": {"data": 2.3514633019369104, "label": "train_mad", "epoch": 10, "counter": 10}},
{"train_mse": {"data": 33.03302141968519, "label": "train_mse", "epoch": 10, "counter": 10}},
{"train_mape": {"data": 93.80782097968692, "label": "train_mape", "epoch": 10, "counter": 10}},
{"train_msle": {"data": 1.028558406760564, "label": "train_msle", "epoch": 10, "counter": 10}},
{"train_r2": {"data": 0.09912450708926457, "label": "train_r2", "epoch": 10, "counter": 10}},
{"train_kappa": {"data": 0.5292481853555016, "label": "train_kappa", "epoch": 10, "counter": 10}},
{"val_mad": {"data": 1.9435710123114451, "label": "val_mad", "epoch": 10, "counter": 10}},
{"val_mse": {"data": 48.619899725797566, "label": "val_mse", "epoch": 10, "counter": 10}},
{"val_mape": {"data": 61.84428178611543, "label": "val_mape", "epoch": 10, "counter": 10}},
{"val_msle": {"data": 0.6914003478482328, "label": "val_msle", "epoch": 10, "counter": 10}},
{"val_r2": {"data": 0.2124548735859796, "label": "val_r2", "epoch": 10, "counter": 10}},
{"val_kappa": {"data": 0.636287504343859, "label": "val_kappa", "epoch": 10, "counter": 10}},
{"train_mad": {"data": 2.3412515713517417, "label": "train_mad", "epoch": 11, "counter": 11}},
{"train_mse": {"data": 32.94946848538551, "label": "train_mse", "epoch": 11, "counter": 11}},
{"train_mape": {"data": 92.47024642658783, "label": "train_mape", "epoch": 11, "counter": 11}},
{"train_msle": {"data": 1.010193895987369, "label": "train_msle", "epoch": 11, "counter": 11}},
{"train_r2": {"data": 0.10143806126384225, "label": "train_r2", "epoch": 11, "counter": 11}},
{"train_kappa": {"data": 0.536483315136951, "label": "train_kappa", "epoch": 11, "counter": 11}},
{"val_mad": {"data": 1.9436638768297203, "label": "val_mad", "epoch": 11, "counter": 11}},
{"val_mse": {"data": 49.304799543605235, "label": "val_mse", "epoch": 11, "counter": 11}},
{"val_mape": {"data": 59.206901008255905, "label": "val_mape", "epoch": 11, "counter": 11}},
{"val_msle": {"data": 0.6764503317883938, "label": "val_msle", "epoch": 11, "counter": 11}},
{"val_r2": {"data": 0.2013608664687645, "label": "val_r2", "epoch": 11, "counter": 11}},
{"val_kappa": {"data": 0.6256556052188623, "label": "val_kappa", "epoch": 11, "counter": 11}},
{"train_mad": {"data": 2.319072147342361, "label": "train_mad", "epoch": 12, "counter": 12}},
{"train_mse": {"data": 32.801737232804996, "label": "train_mse", "epoch": 12, "counter": 12}},
{"train_mape": {"data": 90.67477114980692, "label": "train_mape", "epoch": 12, "counter": 12}},
{"train_msle": {"data": 0.9861213545769032, "label": "train_msle", "epoch": 12, "counter": 12}},
{"train_r2": {"data": 0.10552704532977808, "label": "train_r2", "epoch": 12, "counter": 12}},
{"train_kappa": {"data": 0.5453305079573564, "label": "train_kappa", "epoch": 12, "counter": 12}},
{"val_mad": {"data": 1.9119333158222014, "label": "val_mad", "epoch": 12, "counter": 12}},
{"val_mse": {"data": 47.22147224337231, "label": "val_mse", "epoch": 12, "counter": 12}},
{"val_mape": {"data": 64.25939842106261, "label": "val_mape", "epoch": 12, "counter": 12}},
{"val_msle": {"data": 0.6528894887847154, "label": "val_msle", "epoch": 12, "counter": 12}},
{"val_r2": {"data": 0.2351066016775346, "label": "val_r2", "epoch": 12, "counter": 12}},
{"val_kappa": {"data": 0.668007598424703, "label": "val_kappa", "epoch": 12, "counter": 12}},
{"train_mad": {"data": 2.306497591416348, "label": "train_mad", "epoch": 13, "counter": 13}},
{"train_mse": {"data": 32.36440294044408, "label": "train_mse", "epoch": 13, "counter": 13}},
{"train_mape": {"data": 89.76445361681075, "label": "train_mape", "epoch": 13, "counter": 13}},
{"train_msle": {"data": 0.9729480034150435, "label": "train_msle", "epoch": 13, "counter": 13}},
{"train_r2": {"data": 0.11739856883290833, "label": "train_r2", "epoch": 13, "counter": 13}},
{"train_kappa": {"data": 0.5498412008313603, "label": "train_kappa", "epoch": 13, "counter": 13}},
{"val_mad": {"data": 1.9092297693096125, "label": "val_mad", "epoch": 13, "counter": 13}},
{"val_mse": {"data": 46.40578301259856, "label": "val_mse", "epoch": 13, "counter": 13}},
{"val_mape": {"data": 65.59933157707867, "label": "val_mape", "epoch": 13, "counter": 13}},
{"val_msle": {"data": 0.6331552159397223, "label": "val_msle", "epoch": 13, "counter": 13}},
{"val_r2": {"data": 0.2483191356808373, "label": "val_r2", "epoch": 13, "counter": 13}},
{"val_kappa": {"data": 0.6819888232343507, "label": "val_kappa", "epoch": 13, "counter": 13}},
{"train_mad": {"data": 2.3011876639635767, "label": "train_mad", "epoch": 14, "counter": 14}},
{"train_mse": {"data": 33.09667439186239, "label": "train_mse", "epoch": 14, "counter": 14}},
{"train_mape": {"data": 88.45445068745433, "label": "train_mape", "epoch": 14, "counter": 14}},
{"train_msle": {"data": 0.9564931982611848, "label": "train_msle", "epoch": 14, "counter": 14}},
{"train_r2": {"data": 0.09737668033698221, "label": "train_r2", "epoch": 14, "counter": 14}},
{"train_kappa": {"data": 0.5563960830072117, "label": "train_kappa", "epoch": 14, "counter": 14}},
{"val_mad": {"data": 1.8510589111111577, "label": "val_mad", "epoch": 14, "counter": 14}},
{"val_mse": {"data": 48.008997270961885, "label": "val_mse", "epoch": 14, "counter": 14}},
{"val_mape": {"data": 57.804939034807624, "label": "val_mape", "epoch": 14, "counter": 14}},
{"val_msle": {"data": 0.6173567795448703, "label": "val_msle", "epoch": 14, "counter": 14}},
{"val_r2": {"data": 0.22235027143199626, "label": "val_r2", "epoch": 14, "counter": 14}},
{"val_kappa": {"data": 0.6636221200262677, "label": "val_kappa", "epoch": 14, "counter": 14}}
]